mutagene/__init__.py
mutagene/__main__.py
mutagene/benchmark.py
mutagene/deconstructsigs.py
mutagene/dna.py
mutagene/gdc.py
mutagene/generate_benchmark.py
mutagene/identify.py
mutagene/io.py
mutagene/multiple_benchmark.py
mutagene/mutability.py
mutagene/nci60.py
mutagene/nmf.py
mutagene/profile.py
mutagene/pymutagene.py
mutagene/version.py
mutagene-0.8.5.1.data/scripts/mutagene
mutagene-0.8.5.1.dist-info/LICENSE
mutagene-0.8.5.1.dist-info/METADATA
mutagene-0.8.5.1.dist-info/WHEEL
mutagene-0.8.5.1.dist-info/top_level.txt
mutagene-0.8.5.1.dist-info/RECORD
