Metadata-Version: 2.1
Name: mutagene
Version: 0.8.5.1
Summary: Mutational analysis with Python
Home-page: http://www.ncbi.nlm.nih.gov/projects/mutagene/
Author: Alexander Goncearenco
Author-email: alexandr.goncearenco@nih.gov
License: Public Domain
Keywords: bioinformatics cancer mutations
Platform: UNKNOWN
Classifier: Programming Language :: Python :: 3 :: Only
Classifier: Operating System :: OS Independent
Classifier: License :: Public Domain
Classifier: Development Status :: 4 - Beta
Classifier: Intended Audience :: Science/Research
Classifier: Topic :: Scientific/Engineering :: Bio-Informatics
Classifier: Topic :: Scientific/Engineering :: Medical Science Apps.
Classifier: Environment :: Console
Requires-Dist: bayesian-optimization
Requires-Dist: clustergrammer
Requires-Dist: numpy
Requires-Dist: pandas
Requires-Dist: requests
Requires-Dist: scikit-learn
Requires-Dist: scipy
Requires-Dist: statsmodels
Requires-Dist: twobitreader
Requires-Dist: tqdm
